dweet2ser/__init__.py
dweet2ser/__main__.py
dweet2ser/_configure.py
dweet2ser/device_bus.py
dweet2ser/local_device.py
dweet2ser/remote_device.py
dweet2ser/session.py
dweet2ser/settings.py
dweet2ser/utils.py
dweet2ser/cli/__init__.py
dweet2ser/cli/cli.py
dweet2ser/cli/interface.py
dweet2ser/dweepy/__init__.py
dweet2ser/dweepy/api.py
dweet2ser/dweepy/streaming.py
dweet2ser/skiracetiming/__init__.py
dweet2ser/skiracetiming/translate.py
dweet2ser/webapp/__init__.py
dweet2ser/webapp/socketing.py
dweet2ser/webapp/views.py
dweet2ser/webapp/static/favicon.ico
dweet2ser/webapp/static/jquery-3.6.0.min.js
dweet2ser/webapp/static/site.css
dweet2ser/webapp/static/site.js
dweet2ser/webapp/templates/home.html
dweet2ser-0.4.0.dist-info/LICENSE
dweet2ser-0.4.0.dist-info/METADATA
dweet2ser-0.4.0.dist-info/WHEEL
dweet2ser-0.4.0.dist-info/entry_points.txt
dweet2ser-0.4.0.dist-info/top_level.txt
dweet2ser-0.4.0.dist-info/RECORD
