Metadata-Version: 2.1
Name: dweet2ser
Version: 0.4.0
Summary: A dweet.io <-> serial interface
Home-page: https://github.com/zhenry9/dweet2ser
Author: Zach Henry
Author-email: zhenry9@gmail.com
License: UNKNOWN
Download-URL: https://github.com/zhenry9/dweet2ser/archive/0.4.0.tar.gz
Platform: UNKNOWN
Classifier: Programming Language :: Python :: 3
Classifier: Development Status :: 3 - Alpha
Classifier: Intended Audience :: Developers
Classifier: License :: OSI Approved :: GNU General Public License (GPL)
Classifier: Natural Language :: English
Requires-Python: >=3.6
Requires-Dist: colorama (<1,>=0.4.4)
Requires-Dist: Flask (<2,>=1.1.2)
Requires-Dist: Flask-SocketIO (<6,>=5.0.1)
Requires-Dist: pyserial (<4,>=3.5)
Requires-Dist: requests (<3,>=2.25.1)
Requires-Dist: termcolor (<2,>=1.1.0)
Requires-Dist: psutil (<6,>=5.8.0)
